tfr2human/__init__.py
tfr2human/parser.py
tfr2human/utils.py
tfr2human-0.0.0.3.dist-info/METADATA
tfr2human-0.0.0.3.dist-info/WHEEL
tfr2human-0.0.0.3.dist-info/entry_points.txt
tfr2human-0.0.0.3.dist-info/top_level.txt
tfr2human-0.0.0.3.dist-info/RECORD
